hot_import/__init__.py
hot_import/hot_import.py
test_import/__init__.py
test_import/test.py
hot_import-3.1.0.dist-info/LICENSE
hot_import-3.1.0.dist-info/METADATA
hot_import-3.1.0.dist-info/WHEEL
hot_import-3.1.0.dist-info/top_level.txt
hot_import-3.1.0.dist-info/RECORD
