Metadata-Version: 2.2
Name: hot-import
Version: 3.1.0
Summary: hot-reload for python packages 
Home-page: https://github.com/ThePhoenix78/hot-import
Download-URL: https://github.com/ThePhoenix78/hot-import/tarball/master
Author: ThePhoenix78
Author-email: thephoenix788@gmail.com
License: MIT
Keywords: hot-reload,live reload,live update,hot reload
Classifier: Programming Language :: Python :: 3
Classifier: License :: OSI Approved :: MIT License
Classifier: Operating System :: OS Independent
Requires-Python: >=3.6
License-File: LICENSE
Requires-Dist: watchdog
Dynamic: author
Dynamic: author-email
Dynamic: classifier
Dynamic: description
Dynamic: description-content-type
Dynamic: download-url
Dynamic: home-page
Dynamic: keywords
Dynamic: license
Dynamic: requires-dist
Dynamic: requires-python
Dynamic: summary
